emborg/__init__.py
emborg/collection.py
emborg/command.py
emborg/emborg.py
emborg/help.py
emborg/hooks.py
emborg/main.py
emborg/overdue.py
emborg/patterns.py
emborg/preferences.py
emborg/python.py
emborg/shlib.py
emborg/utilities.py
emborg-1.42.dist-info/entry_points.txt
emborg-1.42.dist-info/licenses/LICENSE
emborg-1.42.dist-info/WHEEL
emborg-1.42.dist-info/METADATA
emborg-1.42.dist-info/RECORD
