Metadata-Version: 2.4
Name: emborg
Version: 1.42
Summary: Borg front end.
Keywords: emborg,borg,borgbackup,borgmatic,vorta,backups
Author: Ken Kundert
Author-email: emborg@nurdletech.com
Requires-Python: >=3.6
Classifier: Development Status :: 5 - Production/Stable
Classifier: Environment :: Console
Classifier: Intended Audience :: End Users/Desktop
Classifier: License :: OSI Approved :: GNU General Public License v3 or later (GPLv3+)
Classifier: Natural Language :: English
Classifier: Operating System :: POSIX :: Linux
Classifier: Programming Language :: Python :: 3
Classifier: Topic :: Utilities
License-File: LICENSE
Requires-Dist: appdirs
Requires-Dist: arrow
Requires-Dist: docopt
Requires-Dist: inform>=1.31
Requires-Dist: nestedtext
Requires-Dist: quantiphy
Requires-Dist: requests
Requires-Dist: avendesora ; extra == "avendesora"
Project-URL: changelog, https://emborg.readthedocs.io/en/latest/releases.html
Project-URL: documentation, https://emborg.readthedocs.io
Project-URL: homepage, https://emborg.readthedocs.io
Project-URL: repository, https://github.com/kenkundert/emborg
Provides-Extra: avendesora
